{"SURVIVAL":{"potions":[],"armorContents":{},"offHandItem":{"==":"org.bukkit.inventory.ItemStack","v":1976,"type":"AIR","amount":0},"enderChestContents":{},"inventoryContents":{"28":{"==":"org.bukkit.inventory.ItemStack","v":1976,"type":"RED_DYE","amount":64},"29":{"==":"org.bukkit.inventory.ItemStack","v":1976,"type":"CHEST"},"30":{"==":"org.bukkit.inventory.ItemStack","v":1976,"type":"ORANGE_DYE"},"31":{"==":"org.bukkit.inventory.ItemStack","v":1976,"type":"YELLOW_DYE"},"32":{"==":"org.bukkit.inventory.ItemStack","v":1976,"type":"GREEN_DYE"},"33":{"==":"org.bukkit.inventory.ItemStack","v":1976,"type":"BLUE_DYE"},"34":{"==":"org.bukkit.inventory.ItemStack","v":1976,"type":"PURPLE_DYE"},"35":{"==":"org.bukkit.inventory.ItemStack","v":1976,"type":"PINK_DYE"},"0":{"==":"org.bukkit.inventory.ItemStack","v":1976,"type":"BRICK_STAIRS"},"1":{"==":"org.bukkit.inventory.ItemStack","v":1976,"type":"END_CRYSTAL"},"2":{"==":"org.bukkit.inventory.ItemStack","v":1976,"type":"OBSIDIAN"},"3":{"==":"org.bukkit.inventory.ItemStack","v":1976,"type":"GLASS_PANE"},"4":{"==":"org.bukkit.inventory.ItemStack","v":1976,"type":"DAYLIGHT_DETECTOR"},"5":{"==":"org.bukkit.inventory.ItemStack","v":1976,"type":"REDSTONE_LAMP"},"6":{"==":"org.bukkit.inventory.ItemStack","v":1976,"type":"OAK_SLAB"},"7":{"==":"org.bukkit.inventory.ItemStack","v":1976,"type":"REPEATER"},"8":{"==":"org.bukkit.inventory.ItemStack","v":1976,"type":"OAK_SIGN"}},"stats":{"ex":"0.0","ma":"300","fl":"20","el":"0","hp":"20.0","xp":"0.0","txp":"0","fd":"0.0","sa":"5.0","ft":"-20","ra":"300"}}}