{"stats":{"minecraft:custom":{"minecraft:jump":107,"minecraft:time_since_rest":445,"minecraft:leave_game":1,"minecraft:deaths":1,"minecraft:play_one_minute":4043,"minecraft:damage_taken":260,"minecraft:sprint_one_cm":14228,"minecraft:walk_on_water_one_cm":1123,"minecraft:time_since_death":394,"minecraft:walk_one_cm":9058,"minecraft:fall_one_cm":3067,"minecraft:fly_one_cm":17878},"minecraft:picked_up":{"minecraft:dirt":1},"minecraft:used":{"minecraft:dirt":1},"minecraft:mined":{"minecraft:grass_block":1}},"DataVersion":1976}